{"count":5,"list":[{"desc":"臺灣桃園地方法院 106 年度 審原訴 字第 20 號判決(106.06.01)","href":"data.aspx?ty=JD&id=TYDM%2c106%2c%e5%af%a9%e5%8e%9f%e8%a8%b4%2c20%2c20170601%2c1","red":0},{"desc":"臺灣高等法院 106 年度 原上訴 字第 73 號判決(106.11.07)","href":"data.aspx?ty=JD&id=TPHM%2c106%2c%e5%8e%9f%e4%b8%8a%e8%a8%b4%2c73%2c20171107%2c1","red":0},{"desc":"最高法院 107 年度 台上 字第 2386 號判決(107.06.28)","href":"data.aspx?ty=JD&id=TPSM%2c107%2c%e5%8f%b0%e4%b8%8a%2c2386%2c20180628%2c1","red":0},{"desc":"臺灣高等法院 107 年度 原上更一 字第 2 號判決(107.11.20)","href":"data.aspx?ty=JD&id=TPHM%2c107%2c%e5%8e%9f%e4%b8%8a%e6%9b%b4%e4%b8%80%2c2%2c20181120%2c1","red":0},{"desc":"最高法院 108 年度 台上 字第 3867 號判決(108.12.25)","href":"data.aspx?ty=JD&id=TPSM%2c108%2c%e5%8f%b0%e4%b8%8a%2c3867%2c20191225%2c1","red":0}]}